sfeatpy/__init__.py
sfeatpy/features.py
sfeatpy-0.0.1.dist-info/LICENCE
sfeatpy-0.0.1.dist-info/METADATA
sfeatpy-0.0.1.dist-info/WHEEL
sfeatpy-0.0.1.dist-info/top_level.txt
sfeatpy-0.0.1.dist-info/RECORD
